ydyld/__init__.py
ydyld/demangle.py
ydyld/dyld.py
ydyld/session.py
ydyld-0.0.10.dist-info/METADATA
ydyld-0.0.10.dist-info/WHEEL
ydyld-0.0.10.dist-info/top_level.txt
ydyld-0.0.10.dist-info/RECORD
